{"swagger":"2.0","info":{"version":"2.0.0","title":"test2","contact":{"name":"Team Slots","url":"http://confluence.agilefabric.fr.carrefour.com/display/STR2/01+-+Team+Slots"},"license":{"name":"Carrefour"}},"host":"localhost:4200","basePath":"/runtime/5fc7f9d5e1b7d7320c364058","tags":[{"name":"Authentication Grizzly","description":"JWT token"},{"name":"slot-resources"}],"schemes":["https","http"],"paths":{"/slots/{slot_id}":{"get":{"tags":["slot-resources"],"summary":"Retrieve a slot details by id","description":"<p>Retrieve the details of the given slot id</p>","consumes":["application/json"],"produces":["application/json"],"parameters":[{"name":"slot_id","in":"path","description":"<p>This is the slot identifier</p>","required":true,"type":"string"},{"name":"x-correlation-id","in":"header","description":"<p>This is the correlation id that can be used to link several API requests together</p>","required":false,"type":"string"}],"responses":{"200":{"description":"Ok","examples":{"application/json":[[[{"begin_datetime":"2020-09-01T13:00:00+02:00","cut_off":"2020-09-01T11:00:00+02:00","end_datetime":"2020-09-01T13:30:00+02:00","maximum_capacity":15,"maximum_day_capacity":10,"reference_round":"1001A","service_id":"143","id":"265547","status":"OPEN","stock_range":"201602281A","used_capacity":0,"used_day_capacity":5}]]]},"headers":{"X-Correlation-ID":{"type":"string","description":"This is the correlation id that can be used to link several API requests together"}},"schema":{"$ref":"#/definitions/slot"}},"400":{"description":"<p>Bad Request, return it the error is about client request and not managed by a specific http code</p>","examples":{"application/json":[[[{"code":"BAD_REQUEST","message":"more details about the error"}]]]},"headers":{"X-Correlation-ID":{"type":"string","description":"This is the correlation id that can be used to link several API requests together"}},"schema":{"$ref":"#/definitions/error_response"}},"500":{"description":"<p>Technical error</p>","examples":{"application/json":[[[{"code":"TECHNICAL_ERROR","message":"more details message"}]]]},"headers":{"X-Correlation-ID":{"type":"string","description":"This is the correlation id that can be used to link several API requests together"}},"schema":{"$ref":"#/definitions/error_response"}},"404":{"description":"<ul><li>unkown service_id</li><li>unkown slot id</li></ul>","examples":{"application/json":[[[{"code":"SERVICE_NOT_FOUND"}]]]},"headers":{"X-Correlation-ID":{"type":"string","description":"This is the correlation id that can be used to link several API requests togethe"}},"schema":{"$ref":"#/definitions/error_response"}}}}},"/allroles":{"get":{"tags":["Authentication Grizzly"],"consumes":["application/json"],"produces":["application/json"],"responses":{"200":{"description":"Ok"},"401":{"description":"Unauthorized"},"403":{"description":"Forbidden"}},"security":[{"api_key":[]}]}},"/allusers":{"get":{"tags":["Authentication Grizzly"],"consumes":["application/json"],"produces":["application/json"],"responses":{"200":{"description":"Ok"},"401":{"description":"Unauthorized"},"403":{"description":"Forbidden"}},"security":[{"api_key":[]}]}},"/slots/{slot_id }/bookings/{booking_reference }":{"put":{"tags":["slot-resources"],"summary":"confirm a slot booking","description":"<p>This endpoint allows to confirm a slot booking for the given booking reference and a confirmation reference</p>","consumes":["application/json"],"produces":["application/json"],"parameters":[{"name":"slot_id ","in":"path","description":"<p>This is the slot identifier</p>","required":true,"type":"string"},{"name":"booking_reference ","in":"path","description":"<p>this is the basket_id or order_id provided to book the slot</p>","required":true,"type":"string"},{"name":"authorization ","in":"header","description":"<p>IAM or STS bearer token (JWT)</p>","required":true,"type":"string"},{"name":"x-correlation-id","in":"header","description":"<p>This is the correlation id that can be used to link several API requests together</p>","required":false,"type":"string"},{"in":"body","name":"body","required":false,"schema":{"$ref":"#/definitions/confirm_slot_request"}}],"responses":{"201":{"description":"<p>Created</p>","examples":{"application/json":[[[{"code":"SLOT_CONFIRMED","slot":{"begin_datetime":"2018-09-17T12:59:00","cut_off":"2018-09-17T12:59:00","end_datetime":"2018-09-17T12:59:00","maximum_capacity":10,"maximum_day_capacity":15,"reference_round":"1001A","service_id":"143","id":"2C2B2","status":"OPEN","stock_range":"201602281A","used_capacity":0,"used_day_capacity":10}}]]]},"headers":{"X-Correlation-ID":{"type":"string","description":"This is the correlation id that can be used to link several API requests together"}},"schema":{"$ref":"#/definitions/slot_action_response"}},"400":{"description":"<p>Bad Request, return it the error is about client request<br>and not managed by a specific http code</p>","examples":{"application/json":[[[{"code":"BAD_REQUEST","message":"more details about the error"}]]]},"headers":{"X-Correlation-ID":{"type":"string","description":"This is the correlation id that can be used to link several API requests together"}},"schema":{"$ref":"#/definitions/error_response"}},"401":{"description":"<p>unauthorized, when JWT token:</p><ul><li>is not provided</li><li>is not valid</li></ul>","examples":{"application/json":[[[{"code":"UNAUTHORIZED","message":"more details about the error"}]]]},"headers":{"X-Correlation-ID":{"type":"string","description":"This is the correlation id that can be used to link several API requests together"}},"schema":{"$ref":"#/definitions/error_response"}},"412":{"description":"<ul><li>The slot is CLOSED</li><li>Slot is outdated</li><li>The slot is not yet displayed</li><li>slot full</li><li>tour full</li><li>ppc full</li></ul>","examples":{"application/json":[[[{"code":"SLOT_FULL"}]]]},"headers":{"X-Correlation-ID":{"type":"string","description":"This is the correlation id that can be used to link several API requests together"}},"schema":{"$ref":"#/definitions/error_response"}},"500":{"description":"<p>Technical error</p>","examples":{"application/json":[[[{"code":"TECHNICAL_ERROR","message":"more details message"}]]]},"headers":{"X-Correlation-ID":{"type":"string","description":"This is the correlation id that can be used to link several API requests together"}},"schema":{"$ref":"#/definitions/error_response"}},"403":{"description":"<p>forbidden when for example :</p><ul><li>The STS JWT Token don't contains the right roles</li><li>The user is not allowed to do this actio</li></ul>","examples":{"application/json":[[[{"code":"FORBIDDEN","message":"more details about the error"}]]]},"headers":{"X-Correlation-ID":{"type":"string","description":"This is the correlation id that can be used to link several API requests together"}},"schema":{"$ref":"#/definitions/error_response"}},"404":{"description":"<ul><li>unkown service_id</li><li>unkown slot id</li></ul>","examples":{"application/json":[[[{"code":"SERVICE_NOT_FOUND"}]]]},"headers":{"X-Correlation-ID":{"type":"string","description":"This is the correlation id that can be used to link several API requests together"}},"schema":{"$ref":"#/definitions/error_response"}},"409":{"description":"<p>Store doesn't match with slot</p>","examples":{"application/json":[[[{"code":"SLOT_AND_SERVICE_ID_DOES_NOT_MATCH"}]]]},"headers":{"X-Correlation-ID":{"type":"string","description":"This is the correlation id that can be used to link several API requests together"}},"schema":{"$ref":"#/definitions/error_response"}}}}},"/me":{"get":{"tags":["Authentication Grizzly"],"consumes":["application/json"],"produces":["application/json"],"responses":{"200":{"description":"Ok"},"401":{"description":"Unauthorized"},"403":{"description":"Forbidden"}},"security":[{"api_key":[]}]}},"/signin":{"post":{"tags":["Authentication Grizzly"],"consumes":["application/json"],"produces":["application/json"],"parameters":[{"in":"body","name":"body","description":"SignIn Model","required":true,"schema":{"$ref":"#/definitions/signIn"}}],"responses":{"200":{"description":"Ok"},"401":{"description":"Unauthorized"},"403":{"description":"Forbidden"}}}},"/updateuser":{"put":{"tags":["Authentication Grizzly"],"consumes":["application/json"],"produces":["application/json"],"parameters":[{"name":"username","in":"query","required":false,"type":"string"}],"responses":{"200":{"description":"Ok"},"401":{"description":"Unauthorized"},"403":{"description":"Forbidden"}},"security":[{"api_key":[]}]}},"/slots/{slot_id}/bookings":{"post":{"tags":["slot-resources"],"summary":"Book a slot for a given booking_reference (basket or order)","description":"<p>Create a booking with the given booking_reference<br>and the slot identifier</p>","consumes":["application/json"],"produces":["application/json"],"parameters":[{"name":"slot_id","in":"path","description":"<p>This is the slot identifier</p>","required":true,"type":"string"},{"name":"authorization ","in":"header","description":"<p>IAM or STS bearer token (JWT)</p>","required":true,"type":"string"},{"name":"x-correlation-id","in":"header","description":"<p>This is the correlation id that can be used to link several API requests together</p>","required":false,"type":"string"},{"in":"body","name":"body","required":false,"schema":{"$ref":"#/definitions/book_slot_request"}}],"responses":{"201":{"description":"<p>OK</p>","examples":{"application/json":[[[{"code":"NEW_SLOT_BOOKED","expires":"2020-06-19T15:28:55","slot":{"begin_datetime":"2018-09-17T12:59:00","cut_off":"2018-09-17T12:59:00","end_datetime":"2018-09-17T12:59:00","maximum_capacity":10,"maximum_day_capacity":15,"reference_round":"1001A","service_id":"143","id":"2C2B2","status":"OPEN","stock_range":"201602281A","used_capacity":0,"used_day_capacity":10}}]]]},"headers":{"X-Correlation-ID":{"type":"string","description":"This is the correlation id that can be used to link several API requests together"}},"schema":{"$ref":"#/definitions/book_slot_response"}},"400":{"description":"<p>Bad Request, return it the error is about client request and not managed by a specific http code</p>","examples":{"application/json":[[[{"code":"BAD_REQUEST","message":"more details about the error"}]]]},"headers":{"X-Correlation-ID":{"type":"string","description":"This is the correlation id that can be used to link several API requests together"}},"schema":{"$ref":"#/definitions/error_response"}},"401":{"description":"<p>Unauthorized , when JWT token:</p><ul><li>is not provided</li><li>is not valid</li></ul>","examples":{"application/json":[[[{"code":"UNAUTHORIZED","message":"more details about the error"}]]]},"headers":{"X-Correlation-ID":{"type":"string","description":"This is the correlation id that can be used to link several API requests together"}},"schema":{"$ref":"#/definitions/error_response"}},"412":{"description":"<ul><li>The slot is CLOSED</li><li>Slot is outdated</li><li>The slot is not yet displayed</li><li>slot full</li><li>tour full</li><li>ppc full</li></ul>","examples":{"application/json":[[[{"code":"SLOT_FULL"}]]]},"headers":{"X-Correlation-ID":{"type":"string","description":"This is the correlation id that can be used to link several API requests together"}},"schema":{"$ref":"#/definitions/error_response"}},"500":{"description":"<p>Technical error</p>","examples":{"application/json":[[[{"code":"TECHNICAL_ERROR","message":"more details message"}]]]},"headers":{"X-Correlation-ID":{"type":"string","description":"This is the correlation id that can be used to link several API requests together"}},"schema":{"$ref":"#/definitions/error_response"}},"403":{"description":"<p>Forbidden when for example :</p><ul><li>The STS JWT Token don't contains the right roles</li><li>The user is not allowed to do this action</li></ul>","examples":{"application/json":[[[{"code":"FORBIDDEN","message":"more details about the error"}]]]},"headers":{"X-Correlation-ID":{"type":"string","description":"This is the correlation id that can be used to link several API requests together"}},"schema":{"$ref":"#/definitions/error_response"}},"404":{"description":"<ul><li>unkown service_id</li><li>unkown slot id</li></ul>","examples":{"application/json":[[[{"code":"SERVICE_NOT_FOUND"}]]]},"headers":{"X-Correlation-ID":{"type":"string","description":"This is the correlation id that can be used to link several API requests together"}},"schema":{"$ref":"#/definitions/error_response"}},"409":{"description":"<p>Store doesn't match with slot</p>","examples":{"application/json":[[[{"code":"SLOT_AND_SERVICE_ID_DOES_NOT_MATCH"}]]]},"headers":{"X-Correlation-ID":{"type":"string","description":"This is the correlation id that can be used to link several API requests together"}},"schema":{"$ref":"#/definitions/error_response"}}}}},"/grant":{"put":{"tags":["Authentication Grizzly"],"consumes":["application/json"],"produces":["application/json"],"parameters":[{"name":"username","in":"query","required":false,"type":"string"}],"responses":{"200":{"description":"Ok"},"401":{"description":"Unauthorized"},"403":{"description":"Forbidden"}},"security":[{"api_key":[]}]}},"/deleteuser":{"delete":{"tags":["Authentication Grizzly"],"consumes":["application/json"],"produces":["application/json"],"parameters":[{"name":"username","in":"query","required":false,"type":"string"}],"responses":{"200":{"description":"Ok"},"401":{"description":"Unauthorized"},"403":{"description":"Forbidden"}},"security":[{"api_key":[]}]}},"/signup":{"post":{"tags":["Authentication Grizzly"],"consumes":["application/json"],"produces":["application/json"],"parameters":[{"in":"body","name":"body","required":true}],"responses":{"200":{"description":"Ok"},"401":{"description":"Unauthorized"},"403":{"description":"Forbidden"}}}},"/slots/{slot_id}/bookingsd":{"delete":{"tags":["slot-resources"],"summary":"This endpoint allows to unbook a slot","description":"<p>to unbook you must provide</p><ul><li>the booking_reference : the ID provided to book the slot (basket_id or order_id)<br>or</li><li>the confirmation_reference : the ID provided to confirm the booking (order_id)</li></ul>","consumes":["application/json"],"produces":["application/json"],"parameters":[{"name":"slot_id","in":"path","description":"<p>This is the slot identifier</p>","required":true,"type":"string"},{"name":"x-correlation-id","in":"header","description":"<p>This is the correlation id that can be used to link several API requests together</p>","required":false,"type":"string"},{"name":"service_id ","in":"query","description":"<p>The service identifier of the store to which the slot belongs (this is the meti service ID)</p>","required":true,"type":"string"},{"name":"booking_reference","in":"query","description":"<p>This is the ID provided to book a slot</p>","required":false,"type":"string"},{"name":"confirmation_reference","in":"query","description":"<p>This is the ID provided to confirm a booked slot</p>","required":false,"type":"string"}],"responses":{"201":{"description":"<p>Created</p>","examples":{"application/json":[[[{"code":"SLOT_UNBOOKED","slot":{"begin_datetime":"2018-09-17T12:59:00","cut_off":"2018-09-17T12:59:00","end_datetime":"2018-09-17T12:59:00","maximum_capacity":10,"maximum_day_capacity":15,"reference_round":"1001A","service_id":"143","id":"2C2B2","status":"OPEN","stock_range":"201602281A","used_capacity":0,"used_day_capacity":10}}]]]},"headers":{"X-Correlation-ID":{"type":"string","description":"This is the correlation id that can be used to link several API requests together"}},"schema":{"$ref":"#/definitions/slot_action_response"}},"400":{"description":"<p>Bad Request, return it the error is about client request<br>and not managed by a specific http code</p>","examples":{"application/json":[[[{"code":"BAD_REQUEST","message":"more details about the error"}]]]},"headers":{"X-Correlation-ID":{"type":"string","description":"This is the correlation id that can be used to link several API requests together"}},"schema":{"$ref":"#/definitions/error_response"}},"401":{"description":"<p>unauthorized, when JWT token:</p><ul><li>is not provided</li><li>is not valid</li></ul>","examples":{"application/json":[[[{"code":"UNAUTHORIZED","message":"more details about the error"}]]]},"headers":{"X-Correlation-ID\t":{"type":"string","description":"This is the correlation id that can be used to link several API requests together"}}},"500":{"description":"<p>Technical error</p>","examples":{"application/json":[[[{"code":"TECHNICAL_ERROR","message":"more details message"}]]]},"headers":{"X-Correlation-ID":{"type":"string","description":"This is the correlation id that can be used to link several API requests together"}},"schema":{"$ref":"#/definitions/error_response"}},"403":{"description":"<p>forbidden when for example :</p><ul><li>The STS JWT Token don't contains the right roles</li><li>The user is not allowed to do this action</li></ul>","examples":{"application/json":[[[{"code":"FORBIDDEN","message":"more details about the error"}]]]},"headers":{"X-Correlation-ID":{"type":"string","description":"This is the correlation id that can be used to link several API requests together"}},"schema":{"$ref":"#/definitions/error_response"}},"404":{"description":"<ul><li>unkown service_id</li><li>unkown slot id</li></ul>","examples":{"application/json":[[[{"code":"SERVICE_NOT_FOUND"}]]]},"headers":{"X-Correlation-ID":{"type":"string","description":"This is the correlation id that can be used to link several API requests together"}},"schema":{"$ref":"#/definitions/error_response"}}}}},"/slots":{"get":{"tags":["slot-resources"],"summary":"Retrieve the list of slots of one or several stores","description":"<p>Retrieve the list of slots of one or several stores<br>between the start date and the end date<br>having the given statuts or all slots regardless of the status if no status is selected</p>","consumes":["application/json"],"produces":["application/json"],"parameters":[{"name":"service_id ","in":"query","description":"<p>The service identifier of the store to which the slot belongs (this is the meti service ID)</p>","required":true,"type":"string"},{"name":"start_datetime","in":"query","description":"<p>This is the beginning of the time range to return slots<br>if start_datetime is not provided default value will be today at 00:00:00<br>end_datetime must be present if start_datetime is present</p>","required":false,"type":"string"},{"name":"end_datetime","in":"query","description":"<p>This is the end of the time range to return slots<br>if end_datetime is not provided default value will be</p><ul><li>5 next days for drive</li><li>7 next days for LAD.</li></ul><p>end_datetime must be present if start_datetime is present.</p><p>the difference between start_datetime and end_datetime should be below than 20 days<br>otherwise end_datetime will be ignored and the response will be the list of slots<br>between start_datetime and start_datetime + 20 days</p>","required":false,"type":"string"},{"name":"status","in":"query","description":"<p>The status of slots. default return all slots regardless of the status</p><p><br>&nbsp;</p>","required":false,"type":"string","enum":["COSED","FULL","OPEN"]},{"name":"x-correlation-id","in":"header","description":"<p>This is the correlation id that can be used to link several API requests together</p>","required":false,"type":"string"}],"responses":{"200":{"description":"Ok","examples":{"application/json":[[[[{"begin_datetime":"2018-09-17T12:59:00","cut_off":"2018-09-17T12:59:00","end_datetime":"2018-09-17T12:59:00","maximum_capacity":15,"maximum_day_capacity":10,"reference_round":"1001A","service_id":"143","id":"11A11","status":"OPEN","stock_range":"201602281A","used_capacity":0,"used_day_capacity":5},{"begin_datetime":"2018-09-17T12:59:00","cut_off":"2018-09-17T12:59:00","end_datetime":"2018-09-17T12:59:00","maximum_capacity":10,"maximum_day_capacity":15,"reference_round":"1001A","service_id":"143","id":"2C2B2","status":"FULL","stock_range":"201602281A","used_capacity":0,"used_day_capacity":10},{"begin_datetime":"2018-09-17T12:59:00","cut_off":"2018-09-17T12:59:00","end_datetime":"2018-09-17T12:59:00","maximum_capacity":15,"maximum_day_capacity":10,"reference_round":"1001A","service_id":"143","id":"3F3BD","status":"CLOSED","stock_range":"201602281A","used_capacity":0,"used_day_capacity":5}]]]]},"headers":{"X-Correlation-ID":{"type":"string","description":"This is the correlation id that can be used to link several API requests together"}},"schema":{"type":"array","items":{"$ref":"#/definitions/slot"}}},"400":{"description":"<p>Bad Request, return it the error is about client request<br>and not managed by a specific http code</p>","examples":{"application/json":[[[{"code":"BAD_REQUEST","message":"more details about the error"}]]]},"headers":{"X-Correlation-ID":{"type":"string","description":"This is the correlation id that can be used to link several API requests together"}},"schema":{"$ref":"#/definitions/error_response"}},"500":{"description":"<p>Technical error</p><p>&nbsp;</p>","examples":{"application/json":[[[{"code":"TECHNICAL_ERROR","message":"more details message"}]]]},"headers":{"X-Correlation-ID":{"type":"string","description":"This is the correlation id that can be used to link several API requests together"}},"schema":{"$ref":"#/definitions/error_response"}},"404":{"description":"<ul><li>unkown service_id</li><li>unkown slot id</li></ul>","examples":{"application/json":[[[{"code":"SERVICE_NOT_FOUND"}]]]},"headers":{"X-Correlation-ID":{"type":"string","description":"This is the correlation id that can be used to link several API requests together"}},"schema":{"$ref":"#/definitions/error_response"}}}}},"/activate":{"post":{"tags":["Authentication Grizzly"],"consumes":["application/json"],"produces":["application/json"],"parameters":[{"name":"username","in":"query","required":false,"type":"string"}],"responses":{"200":{"description":"Ok"},"401":{"description":"Unauthorized"},"403":{"description":"Forbidden"}},"security":[{"api_key":[]}]}}},"securityDefinitions":{"api_key":{"description":"Standard Authorization header using the Bearer scheme. \n\n Value example: \"Bearer {token}\"","type":"apiKey","name":"Authorization","in":"header"}},"definitions":{"book_slot_response":{"properties":{"code":{"$ref":"#/definitions/response_code"},"message":{"type":"string","example":"the slot (1234) is CLOSED","description":"  response message, when we need more details than the code. "},"slot":{"$ref":"#/definitions/slot"}},"title":"book_slot_response","description":" The request object needed to book a slot "},"confirm_slot_request":{"properties":{"confirmation_reference":{"type":"string","example":"A00000","description":" An ID that can be used after to unbook the slot if needed. Usually this is the order_id"},"service_id":{"type":"string","example":335,"description":" The service identifier of the store to which the slot belongs (this is the meti service ID) "}},"title":"confirm_slot_request","description":" The request object needed to confirm a slot"},"response_code":{"type":"string","title":"response_code","description":" A list of possible response code used to success or error","enum":[" NEW_SLOT_BOOKED"," SLOT_ALREADY_BOOKED"," SLOT_UPDATED"," SLOT_NOT_FOUND"," CONFIRMED_BOOKING_ALREADY_EXIST"," BOOKING_NOT_FOUND"," BOOKING_REPLACED"," SLOT_AND_METICODE_DOES_NOT_MATCH"," SLOT_CLOSED"," SLOT_NOT_DISPLAYED"," SLOT_IN_PAST"," SLOT_FULL"," DAY_FULL"," TOUR_FULL"," PPC_FULL"," SLOT_OUTDATED"," TOUR_OUTDATED"," SLOT_UNBOOKED"," SLOT_CONFIRMED"," BOOKING_AND_SLOT_DOES_NOT_MATCH"," UNAUTHORIZED"," TOO_MANY_SERVICE_ID"," INVALID_DATE_TIME_RANGE"," BAD_REQUEST"," TECHNICAL_ERROR"," FORBIDDEN"]},"error_response":{"properties":{"code":{"$ref":"#/definitions/response_code"},"message":{"type":"string","example":"the slot (1234) is CLOSED","description":" response message, when we need more details than the code. "}},"title":"error_response","description":" base response format containing code and message"},"signIn":{"properties":{"username":{"type":"string"},"password":{"type":"string"}},"title":"signIn"},"slot_status":{"type":"string","title":"slot_status","description":" The list of possible slot status \n  - OPEN : when booking is possible \n - CLOSED : when slot is CLOSED by shop, although the max capacity is not reached  \n - FULL :  when the day capacity or the slot capacity is reached  \n When slot has the CLOSED or FULL status booking is no longer available ","enum":[" OPEN "," CLOSED "," FULL "]},"book_slot_request":{"properties":{"booking_reference":{"type":"string","example":1324,"description":" this is the basket_id or order_id used to book or confirm the slot "},"service_id":{"type":"string","example":335,"description":" The service identifier of the store to which the slot belongs (this is the meti service ID)"}},"title":"book_slot_request","description":" The request object needed to book a slot"},"slot":{"properties":{"begin_datetime":{"type":"string","example":"2020-09-01T13:00:00+02:00","description":"This is the slot beginning date and time"},"cut_off":{"type":"string","example":"2020-09-01T11:00:00+02:00","description":"Date and time before the slot become unavailable"},"end_datetime":{"type":"string","example":"2020-09-01T13:30:00+02:00","description":"This is the slot ending date and time"},"maximum_capacity":{"type":"number","example":15.0,"description":"This is the maximum slot capacity (number of baskets/orders)"},"maximum_day_capacity":{"type":"number","example":10.0,"description":" It's the maximum capacity of the day defined by the shop"},"reference_round":{"type":"string","example":"1001A","description":" Day ref (1 for monday, 2 for tuesday, 3, 4, 5, 6, 7) + round ref (001, 002, 003, nn) + Week type (A, B, C, x). ! will be available into V2 version"},"service_id":{"type":"string","example":143,"description":" The service identifier of the store to which the slot belongs"},"id":{"type":"string","example":265547,"description":" This is the identifier of the slot "},"status":{"$ref":"#/definitions/slot_status"},"stock_range":{"type":"string","example":"201602281A","description":" concatenation between the day of preparation and 1A, 1B, 2A, 2B, 3A, 3B, 4A, 4B, 5A, 5B ...! will be available into V2 version"},"used_capacity":{"type":"number","example":0.0,"description":" This is the number of baskets/orders already affected to this slot"},"used_day_capacity":{"type":"number","example":5.0,"description":" Total number of baskets/orders on all the slots of the day"}},"title":"slot","description":" A slot details object"},"signUp":{"properties":{"username":{"type":"string"},"password":{"type":"string"},"firstname":{"type":"string"},"lastname":{"type":"string"},"email":{"type":"string"},"phone":{"type":"number"}},"title":"signUp"},"slot_action_response":{"properties":{"code":{"$ref":"#/definitions/response_code"},"message":{"type":"string","example":"the slot (1234) is CLOSED","description":" response message, when we need more details than the code."},"slot":{"$ref":"#/definitions/slot"}},"title":"slot_action_response","description":" a base response format containing code and messag"}}}